MANIFEST.in
setup.cfg
setup.py
comany2country/__init__.py
comany2country/get_country_by_company.py
company2country.egg-info/PKG-INFO
company2country.egg-info/SOURCES.txt
company2country.egg-info/dependency_links.txt
company2country.egg-info/top_level.txt